ftscraper/__init__.py
ftscraper/api.py
ftscraper/search_obj.py
ftscraper/utils.py
ftscraper-1.0.6.dist-info/LICENSE
ftscraper-1.0.6.dist-info/METADATA
ftscraper-1.0.6.dist-info/WHEEL
ftscraper-1.0.6.dist-info/top_level.txt
ftscraper-1.0.6.dist-info/RECORD
