Metadata-Version: 2.1
Name: ftscraper
Version: 1.0.6
Summary: An unofficial API for Financial Times (ft.com)
Home-page: https://github.com/phachara-laohrenu/financialtimes-api-unofficial
Author: Phachara Laohrenu
Author-email: phachara.lahorenu@gmail.com
License: MIT License
Project-URL: Bug Reports, https://github.com/phachara-laohrenu/financialtimes-api-unofficial/issues
Project-URL: Source, https://github.com/phachara-laohrenu/financialtimes-api-unofficial
Keywords: financial-times,financial-times-api,historical-data,financial-data,funds
Platform: UNKNOWN
Classifier: Programming Language :: Python :: 3
Classifier: Programming Language :: Python :: 3.6
Classifier: Programming Language :: Python :: 3.7
Classifier: Programming Language :: Python :: 3.8
Classifier: Programming Language :: Python :: 3.9
Classifier: License :: OSI Approved :: MIT License
Classifier: Intended Audience :: Developers
Classifier: Topic :: Office/Business :: Financial
Classifier: Topic :: Office/Business :: Financial :: Investment
Classifier: Topic :: Scientific/Engineering :: Information Analysis
Classifier: Topic :: Software Development :: Libraries
Requires-Python: >=3.6
Requires-Dist: requests
Requires-Dist: pandas
Requires-Dist: fuzzywuzzy
Requires-Dist: numpy
Requires-Dist: beautifulsoup4
Requires-Dist: PyYAML
Requires-Dist: python-Levenshtein
